{"created_at":"Sat Oct 15 16:44:09 +0000 2011","id":125250617911418881,"id_str":"125250617911418881","text":"@moLifer26 @apple When we find people standing in the middle of blood-soaked rooms saying, \"Siri told me to?\" #noreallyihearvoices","source":"\u003ca href=\"http:\/\/itunes.apple.com\/us\/app\/twitter\/id409789998?mt=12\" rel=\"nofollow\"\u003eTwitter for Mac\u003c\/a\u003e","truncated":false,"in_reply_to_status_id":125250078108684288,"in_reply_to_status_id_str":"125250078108684288","in_reply_to_user_id":71855109,"in_reply_to_user_id_str":"71855109","in_reply_to_screen_name":"moLifer26","user":{"id":14868161,"id_str":"14868161","name":"David Powell","screen_name":"davidpowell","location":"Montgomery County, PA, USA","description":"Dad, writer\/editor, techie, historian. One of those cultural elites you were warned about.","url":"https:\/\/t.co\/oMljUt0PHF","entities":{"url":{"urls":[{"url":"https:\/\/t.co\/oMljUt0PHF","expanded_url":"https:\/\/www.linkedin.com\/in\/powellwrites","display_url":"linkedin.com\/in\/powellwrites","indices":[0,23]}]},"description":{"urls":[]}},"protected":false,"followers_count":705,"friends_count":651,"listed_count":46,"created_at":"Thu May 22 13:27:26 +0000 2008","favourites_count":264,"utc_offset":-18000,"time_zone":"Eastern Time (US & Canada)","geo_enabled":true,"verified":false,"statuses_count":5744,"lang":"en","contributors_enabled":false,"is_translator":false,"is_translation_enabled":false,"profile_background_color":"9AE4E8","profile_background_image_url":"http:\/\/pbs.twimg.com\/profile_background_images\/56703868\/DSC00964_sm.jpg","profile_background_image_url_https":"https:\/\/pbs.twimg.com\/profile_background_images\/56703868\/DSC00964_sm.jpg","profile_background_tile":true,"profile_image_url":"http:\/\/pbs.twimg.com\/profile_images\/529008030994956288\/9tFZZs7v_normal.jpeg","profile_image_url_https":"https:\/\/pbs.twimg.com\/profile_images\/529008030994956288\/9tFZZs7v_normal.jpeg","profile_link_color":"0000FF","profile_sidebar_border_color":"87BC44","profile_sidebar_fill_color":"E0FF92","profile_text_color":"000000","profile_use_background_image":true,"has_extended_profile":false,"default_profile":false,"default_profile_image":false,"following":false,"follow_request_sent":false,"notifications":false},"geo":null,"coordinates":null,"place":null,"contributors":null,"is_quote_status":false,"retweet_count":1,"favorite_count":1,"entities":{"hashtags":[{"text":"noreallyihearvoices","indices":[110,130]}],"symbols":[],"user_mentions":[{"screen_name":"moLifer26","name":"Molly","id":71855109,"id_str":"71855109","indices":[0,10]},{"screen_name":"Apple","name":"@apple","id":380749300,"id_str":"380749300","indices":[11,17]}],"urls":[]},"favorited":false,"retweeted":false,"lang":"en"}