{"created_at":"Sun Oct 16 00:15:18 +0000 2011","id":125364154629492737,"id_str":"125364154629492737","text":"Proof that my dad loves my sis more. RT @AnnaCorinne16 woke up to my dad at my door w my new iphone. he surprised me & went to @apple!","source":"\u003ca href=\"http:\/\/twitter.com\/download\/iphone\" rel=\"nofollow\"\u003eTwitter for iPhone\u003c\/a\u003e","truncated":false,"in_reply_to_status_id":null,"in_reply_to_status_id_str":null,"in_reply_to_user_id":null,"in_reply_to_user_id_str":null,"in_reply_to_screen_name":null,"user":{"id":14915870,"id_str":"14915870","name":"grahamyelton","screen_name":"grahamyelton","location":"a tennessean living in alabama","description":"*obsessive creative disorder* designer, photographer, crafter and aspiring farmer.","url":"http:\/\/t.co\/LVwR44Qvw9","entities":{"url":{"urls":[{"url":"http:\/\/t.co\/LVwR44Qvw9","expanded_url":"http:\/\/www.grahamyelton.com","display_url":"grahamyelton.com","indices":[0,22]}]},"description":{"urls":[]}},"protected":false,"followers_count":353,"friends_count":148,"listed_count":15,"created_at":"Tue May 27 02:18:50 +0000 2008","favourites_count":46,"utc_offset":-21600,"time_zone":"Central Time (US & Canada)","geo_enabled":false,"verified":false,"statuses_count":5915,"lang":"en","contributors_enabled":false,"is_translator":false,"is_translation_enabled":false,"profile_background_color":"FFFFFF","profile_background_image_url":"http:\/\/pbs.twimg.com\/profile_background_images\/802946093\/306a17e8c1abe8649782b4773cc8010e.jpeg","profile_background_image_url_https":"https:\/\/pbs.twimg.com\/profile_background_images\/802946093\/306a17e8c1abe8649782b4773cc8010e.jpeg","profile_background_tile":false,"profile_image_url":"http:\/\/pbs.twimg.com\/profile_images\/513358270409752576\/Rcfui8Ui_normal.jpeg","profile_image_url_https":"https:\/\/pbs.twimg.com\/profile_images\/513358270409752576\/Rcfui8Ui_normal.jpeg","profile_link_color":"807E7E","profile_sidebar_border_color":"FFFFFF","profile_sidebar_fill_color":"F5F5F5","profile_text_color":"B3B3B3","profile_use_background_image":true,"has_extended_profile":false,"default_profile":false,"default_profile_image":false,"following":false,"follow_request_sent":false,"notifications":false},"geo":null,"coordinates":null,"place":null,"contributors":null,"is_quote_status":false,"retweet_count":0,"favorite_count":0,"entities":{"hashtags":[],"symbols":[],"user_mentions":[{"screen_name":"AnnaCorinne16","name":"Anna Corinne","id":24041874,"id_str":"24041874","indices":[40,54]},{"screen_name":"Apple","name":"@apple","id":380749300,"id_str":"380749300","indices":[127,133]}],"urls":[]},"favorited":false,"retweeted":false,"lang":"en"}