{"created_at":"Sun Oct 16 00:20:58 +0000 2011","id":125365581170999296,"id_str":"125365581170999296","text":"Dear @Apple: You must let me turn off iCloud to save bandwidth and NOT delete EVERY document on my iPad. That's BULLSHIT!","source":"\u003ca href=\"http:\/\/twitter.com\/download\/iphone\" rel=\"nofollow\"\u003eTwitter for iPhone\u003c\/a\u003e","truncated":false,"in_reply_to_status_id":null,"in_reply_to_status_id_str":null,"in_reply_to_user_id":null,"in_reply_to_user_id_str":null,"in_reply_to_screen_name":null,"user":{"id":168883597,"id_str":"168883597","name":"Duke Harrington","screen_name":"DirigoDuke","location":"Terra Onde di Mala Gente","description":"Maker and dealer in social gossip, political wisdom and Yankee philosophy. This is a personal account, opinions my own, work account is @NorumbegaNews","url":null,"entities":{"description":{"urls":[]}},"protected":false,"followers_count":1099,"friends_count":1052,"listed_count":58,"created_at":"Wed Jul 21 01:03:35 +0000 2010","favourites_count":636,"utc_offset":-18000,"time_zone":"Eastern Time (US & Canada)","geo_enabled":true,"verified":false,"statuses_count":31086,"lang":"en","contributors_enabled":false,"is_translator":false,"is_translation_enabled":false,"profile_background_color":"C0DEED","profile_background_image_url":"http:\/\/abs.twimg.com\/images\/themes\/theme1\/bg.png","profile_background_image_url_https":"https:\/\/abs.twimg.com\/images\/themes\/theme1\/bg.png","profile_background_tile":false,"profile_image_url":"http:\/\/pbs.twimg.com\/profile_images\/649618632511778816\/ipOwGOEK_normal.jpg","profile_image_url_https":"https:\/\/pbs.twimg.com\/profile_images\/649618632511778816\/ipOwGOEK_normal.jpg","profile_banner_url":"https:\/\/pbs.twimg.com\/profile_banners\/168883597\/1443716021","profile_link_color":"0084B4","profile_sidebar_border_color":"C0DEED","profile_sidebar_fill_color":"DDEEF6","profile_text_color":"333333","profile_use_background_image":true,"has_extended_profile":false,"default_profile":true,"default_profile_image":false,"following":false,"follow_request_sent":false,"notifications":false},"geo":null,"coordinates":null,"place":null,"contributors":null,"is_quote_status":false,"retweet_count":0,"favorite_count":0,"entities":{"hashtags":[],"symbols":[],"user_mentions":[{"screen_name":"Apple","name":"@apple","id":380749300,"id_str":"380749300","indices":[5,11]}],"urls":[]},"favorited":false,"retweeted":false,"lang":"en"}