{"created_at":"Sat Oct 15 21:46:42 +0000 2011","id":125326760769372160,"id_str":"125326760769372160","text":"when is @apple gonna update the fact that i can't see emoji on twitter for mac?","source":"\u003ca href=\"http:\/\/itunes.apple.com\/us\/app\/twitter\/id409789998?mt=12\" rel=\"nofollow\"\u003eTwitter for Mac\u003c\/a\u003e","truncated":false,"in_reply_to_status_id":null,"in_reply_to_status_id_str":null,"in_reply_to_user_id":null,"in_reply_to_user_id_str":null,"in_reply_to_screen_name":null,"user":{"id":36933064,"id_str":"36933064","name":"SherylRaeReid","screen_name":"UmmSugaRae","location":"Nashville, TN","description":"You're not successful until you create a successor...put yourself in a position to help somebody else -Marvin McQuitty, Jr. Live.Laugh.Love","url":"http:\/\/t.co\/xAwwgOYTPs","entities":{"url":{"urls":[{"url":"http:\/\/t.co\/xAwwgOYTPs","expanded_url":"http:\/\/www.BOMB.com","display_url":"BOMB.com","indices":[0,22]}]},"description":{"urls":[]}},"protected":false,"followers_count":1547,"friends_count":469,"listed_count":39,"created_at":"Fri May 01 12:34:18 +0000 2009","favourites_count":133,"utc_offset":-18000,"time_zone":"Eastern Time (US & Canada)","geo_enabled":true,"verified":false,"statuses_count":84541,"lang":"en","contributors_enabled":false,"is_translator":false,"is_translation_enabled":false,"profile_background_color":"9AE4E8","profile_background_image_url":"http:\/\/pbs.twimg.com\/profile_background_images\/15177345\/elephant.jpg","profile_background_image_url_https":"https:\/\/pbs.twimg.com\/profile_background_images\/15177345\/elephant.jpg","profile_background_tile":true,"profile_image_url":"http:\/\/pbs.twimg.com\/profile_images\/2846211339\/6167f88f60a174c4417359bef9074a95_normal.png","profile_image_url_https":"https:\/\/pbs.twimg.com\/profile_images\/2846211339\/6167f88f60a174c4417359bef9074a95_normal.png","profile_banner_url":"https:\/\/pbs.twimg.com\/profile_banners\/36933064\/1393625405","profile_link_color":"0084B4","profile_sidebar_border_color":"BDDCAD","profile_sidebar_fill_color":"DDFFCC","profile_text_color":"333333","profile_use_background_image":true,"has_extended_profile":false,"default_profile":false,"default_profile_image":false,"following":false,"follow_request_sent":false,"notifications":false},"geo":null,"coordinates":null,"place":null,"contributors":null,"is_quote_status":false,"retweet_count":0,"favorite_count":0,"entities":{"hashtags":[],"symbols":[],"user_mentions":[{"screen_name":"Apple","name":"@apple","id":380749300,"id_str":"380749300","indices":[8,14]}],"urls":[]},"favorited":false,"retweeted":false,"lang":"en"}