{"created_at":"Mon Oct 17 18:00:27 +0000 2011","id":125994596336533504,"id_str":"125994596336533504","text":"Lies @apple. the battery on this new iPhone4S is definitely not any better.","source":"\u003ca href=\"http:\/\/itunes.apple.com\/us\/app\/twitter\/id409789998?mt=12\" rel=\"nofollow\"\u003eTwitter for Mac\u003c\/a\u003e","truncated":false,"in_reply_to_status_id":null,"in_reply_to_status_id_str":null,"in_reply_to_user_id":null,"in_reply_to_user_id_str":null,"in_reply_to_screen_name":null,"user":{"id":17972431,"id_str":"17972431","name":"\u25b3CBM\u25b3","screen_name":"CBM","location":"the world is global, baby","description":"\u2b50\ufe0fcurator @summit. green smoothies @hustleandkale. founded @audienceio. adviser @SECONDHOMELDN #kale #dance #sleep (repeat)","url":"http:\/\/t.co\/MqRmmufhqD","entities":{"url":{"urls":[{"url":"http:\/\/t.co\/MqRmmufhqD","expanded_url":"http:\/\/Instagram.com\/cbm","display_url":"Instagram.com\/cbm","indices":[0,22]}]},"description":{"urls":[]}},"protected":false,"followers_count":13252,"friends_count":993,"listed_count":946,"created_at":"Mon Dec 08 20:32:29 +0000 2008","favourites_count":1051,"utc_offset":0,"time_zone":"London","geo_enabled":true,"verified":false,"statuses_count":32159,"lang":"en","contributors_enabled":false,"is_translator":false,"is_translation_enabled":false,"profile_background_color":"022330","profile_background_image_url":"http:\/\/pbs.twimg.com\/profile_background_images\/648418277\/6f13zwlubmq2hnrcltr1.jpeg","profile_background_image_url_https":"https:\/\/pbs.twimg.com\/profile_background_images\/648418277\/6f13zwlubmq2hnrcltr1.jpeg","profile_background_tile":true,"profile_image_url":"http:\/\/pbs.twimg.com\/profile_images\/475574516647985152\/eF-rUNlN_normal.jpeg","profile_image_url_https":"https:\/\/pbs.twimg.com\/profile_images\/475574516647985152\/eF-rUNlN_normal.jpeg","profile_banner_url":"https:\/\/pbs.twimg.com\/profile_banners\/17972431\/1440696530","profile_link_color":"9266CC","profile_sidebar_border_color":"A8C7F7","profile_sidebar_fill_color":"C0DFEC","profile_text_color":"333333","profile_use_background_image":true,"has_extended_profile":false,"default_profile":false,"default_profile_image":false,"following":false,"follow_request_sent":false,"notifications":false},"geo":null,"coordinates":null,"place":null,"contributors":null,"is_quote_status":false,"retweet_count":1,"favorite_count":1,"entities":{"hashtags":[],"symbols":[],"user_mentions":[{"screen_name":"Apple","name":"@apple","id":380749300,"id_str":"380749300","indices":[5,11]}],"urls":[]},"favorited":false,"retweeted":false,"lang":"en"}