{"created_at":"Mon Oct 17 16:24:32 +0000 2011","id":125970459404673026,"id_str":"125970459404673026","text":"RT @mpastrana: RT @apple no pasa nada, todo esta bien, no pasa nada, todo esta en orden http:\/\/t.co\/zwECWhD","source":"\u003ca href=\"http:\/\/twitter.com\" rel=\"nofollow\"\u003eTwitter Web Client\u003c\/a\u003e","truncated":false,"in_reply_to_status_id":null,"in_reply_to_status_id_str":null,"in_reply_to_user_id":null,"in_reply_to_user_id_str":null,"in_reply_to_screen_name":null,"user":{"id":64417721,"id_str":"64417721","name":"Mario Hernandez \u264a","screen_name":"MarioHdzV","location":"24.031923,-104.635967","description":"Wonderland is not a nice place to live.","url":"http:\/\/t.co\/nJyX9cz0dc","entities":{"url":{"urls":[{"url":"http:\/\/t.co\/nJyX9cz0dc","expanded_url":"http:\/\/hdzmario.blogspot.com\/","display_url":"hdzmario.blogspot.com","indices":[0,22]}]},"description":{"urls":[]}},"protected":false,"followers_count":193,"friends_count":200,"listed_count":4,"created_at":"Mon Aug 10 14:36:02 +0000 2009","favourites_count":956,"utc_offset":null,"time_zone":null,"geo_enabled":true,"verified":false,"statuses_count":13824,"lang":"es","contributors_enabled":false,"is_translator":false,"is_translation_enabled":false,"profile_background_color":"022330","profile_background_image_url":"http:\/\/abs.twimg.com\/images\/themes\/theme15\/bg.png","profile_background_image_url_https":"https:\/\/abs.twimg.com\/images\/themes\/theme15\/bg.png","profile_background_tile":false,"profile_image_url":"http:\/\/pbs.twimg.com\/profile_images\/606250404498698240\/imEajvYT_normal.jpg","profile_image_url_https":"https:\/\/pbs.twimg.com\/profile_images\/606250404498698240\/imEajvYT_normal.jpg","profile_banner_url":"https:\/\/pbs.twimg.com\/profile_banners\/64417721\/1368312422","profile_link_color":"0084B4","profile_sidebar_border_color":"A8C7F7","profile_sidebar_fill_color":"C0DFEC","profile_text_color":"333333","profile_use_background_image":true,"has_extended_profile":true,"default_profile":false,"default_profile_image":false,"following":false,"follow_request_sent":false,"notifications":false},"geo":null,"coordinates":null,"place":null,"contributors":null,"retweeted_status":{"created_at":"Thu Aug 25 00:07:37 +0000 2011","id":106518051519864832,"id_str":"106518051519864832","text":"RT @apple no pasa nada, todo esta bien, no pasa nada, todo esta en orden http:\/\/t.co\/zwECWhD","source":"\u003ca href=\"http:\/\/twitpic.com\" rel=\"nofollow\"\u003eTwitpic\u003c\/a\u003e","truncated":false,"in_reply_to_status_id":null,"in_reply_to_status_id_str":null,"in_reply_to_user_id":null,"in_reply_to_user_id_str":null,"in_reply_to_screen_name":null,"user":{"id":14378372,"id_str":"14378372","name":"Ophelia Pastrana \u26a7","screen_name":"OphCourse","location":"FB: \/OphCourse","description":"LGBT, Media Girl y Exgur\u00fa. Corro, grito y empujo. Me topan en Platzi \/email: oph@oph.la","url":"https:\/\/t.co\/FJxcIslFFi","entities":{"url":{"urls":[{"url":"https:\/\/t.co\/FJxcIslFFi","expanded_url":"http:\/\/oph.la","display_url":"oph.la","indices":[0,23]}]},"description":{"urls":[]}},"protected":false,"followers_count":739909,"friends_count":10818,"listed_count":1403,"created_at":"Sun Apr 13 22:06:07 +0000 2008","favourites_count":51846,"utc_offset":-21600,"time_zone":"Mexico City","geo_enabled":true,"verified":true,"statuses_count":78007,"lang":"en","contributors_enabled":false,"is_translator":false,"is_translation_enabled":false,"profile_background_color":"131516","profile_background_image_url":"http:\/\/pbs.twimg.com\/profile_background_images\/637097341753757698\/hX6Kb-hE.jpg","profile_background_image_url_https":"https:\/\/pbs.twimg.com\/profile_background_images\/637097341753757698\/hX6Kb-hE.jpg","profile_background_tile":true,"profile_image_url":"http:\/\/pbs.twimg.com\/profile_images\/646472084005060612\/1Jsn2FC6_normal.jpg","profile_image_url_https":"https:\/\/pbs.twimg.com\/profile_images\/646472084005060612\/1Jsn2FC6_normal.jpg","profile_banner_url":"https:\/\/pbs.twimg.com\/profile_banners\/14378372\/1441811366","profile_link_color":"E50000","profile_sidebar_border_color":"FFFFFF","profile_sidebar_fill_color":"EFEFEF","profile_text_color":"333333","profile_use_background_image":true,"has_extended_profile":true,"default_profile":false,"default_profile_image":false,"following":false,"follow_request_sent":false,"notifications":false},"geo":null,"coordinates":null,"place":null,"contributors":null,"is_quote_status":false,"retweet_count":63,"favorite_count":5,"entities":{"hashtags":[],"symbols":[],"user_mentions":[{"screen_name":"Apple","name":"@apple","id":380749300,"id_str":"380749300","indices":[3,9]}],"urls":[{"url":"http:\/\/t.co\/zwECWhD","expanded_url":"http:\/\/twitpic.com\/6ast8h","display_url":"twitpic.com\/6ast8h","indices":[73,92]}]},"favorited":false,"retweeted":false,"possibly_sensitive":false,"possibly_sensitive_appealable":false,"lang":"es"},"is_quote_status":false,"retweet_count":63,"favorite_count":0,"entities":{"hashtags":[],"symbols":[],"user_mentions":[{"screen_name":"MPastrana","name":"Milton Jose Pastrana","id":1611470706,"id_str":"1611470706","indices":[3,13]},{"screen_name":"Apple","name":"@apple","id":380749300,"id_str":"380749300","indices":[18,24]}],"urls":[{"url":"http:\/\/t.co\/zwECWhD","expanded_url":"http:\/\/twitpic.com\/6ast8h","display_url":"twitpic.com\/6ast8h","indices":[88,107]}]},"favorited":false,"retweeted":false,"possibly_sensitive":false,"possibly_sensitive_appealable":false,"lang":"es"}