{"created_at":"Wed Oct 19 03:02:02 +0000 2011","id":126493280832724992,"id_str":"126493280832724992","text":"Recent study of #Google CTR reveals that top three positions in #GoogleSearch receive 35% of traffic.... http:\/\/t.co\/IHts3PyW","source":"\u003ca href=\"http:\/\/www.facebook.com\/twitter\" rel=\"nofollow\"\u003eFacebook\u003c\/a\u003e","truncated":false,"in_reply_to_status_id":null,"in_reply_to_status_id_str":null,"in_reply_to_user_id":null,"in_reply_to_user_id_str":null,"in_reply_to_screen_name":null,"user":{"id":112894509,"id_str":"112894509","name":"CWD","screen_name":"CreatorWeb","location":"Australia","description":"Creator Web Design and Mobile Apps","url":"http:\/\/t.co\/bHyxAtkfRQ","entities":{"url":{"urls":[{"url":"http:\/\/t.co\/bHyxAtkfRQ","expanded_url":"http:\/\/www.creatorwebdesign.com","display_url":"creatorwebdesign.com","indices":[0,22]}]},"description":{"urls":[]}},"protected":false,"followers_count":246,"friends_count":281,"listed_count":1,"created_at":"Wed Feb 10 01:50:07 +0000 2010","favourites_count":1,"utc_offset":36000,"time_zone":"Brisbane","geo_enabled":true,"verified":false,"statuses_count":465,"lang":"en","contributors_enabled":false,"is_translator":false,"is_translation_enabled":false,"profile_background_color":"022330","profile_background_image_url":"http:\/\/abs.twimg.com\/images\/themes\/theme15\/bg.png","profile_background_image_url_https":"https:\/\/abs.twimg.com\/images\/themes\/theme15\/bg.png","profile_background_tile":false,"profile_image_url":"http:\/\/pbs.twimg.com\/profile_images\/690465458\/CWD-Hosting-logo-Twitter_normal.jpg","profile_image_url_https":"https:\/\/pbs.twimg.com\/profile_images\/690465458\/CWD-Hosting-logo-Twitter_normal.jpg","profile_link_color":"0084B4","profile_sidebar_border_color":"A8C7F7","profile_sidebar_fill_color":"C0DFEC","profile_text_color":"333333","profile_use_background_image":true,"has_extended_profile":false,"default_profile":false,"default_profile_image":false,"following":false,"follow_request_sent":false,"notifications":false},"geo":null,"coordinates":null,"place":null,"contributors":null,"is_quote_status":false,"retweet_count":0,"favorite_count":0,"entities":{"hashtags":[{"text":"Google","indices":[16,23]},{"text":"GoogleSearch","indices":[64,77]}],"symbols":[],"user_mentions":[],"urls":[{"url":"http:\/\/t.co\/IHts3PyW","expanded_url":"http:\/\/fb.me\/1cJCdfTAV","display_url":"fb.me\/1cJCdfTAV","indices":[105,125]}]},"favorited":false,"retweeted":false,"possibly_sensitive":false,"possibly_sensitive_appealable":false,"lang":"en"}