{"created_at":"Wed Oct 19 05:36:36 +0000 2011","id":126532178082410496,"id_str":"126532178082410496","text":"#Google search to have default encryption http:\/\/t.co\/rwgKPbGu","source":"\u003ca href=\"http:\/\/www.techfish.co.uk\" rel=\"nofollow\"\u003eTechfish News\u003c\/a\u003e","truncated":false,"in_reply_to_status_id":null,"in_reply_to_status_id_str":null,"in_reply_to_user_id":null,"in_reply_to_user_id_str":null,"in_reply_to_screen_name":null,"user":{"id":374494006,"id_str":"374494006","name":"Gabriele Biondo","screen_name":"gb700823","location":"","description":"CISSP, CISM, ITIL, OPST, ISO 27 Lead Auditor, and  cyberpunk inside.\nInterested into ICTSecurity, Math, and Sushi.","url":"http:\/\/t.co\/jbGSkBrhrk","entities":{"url":{"urls":[{"url":"http:\/\/t.co\/jbGSkBrhrk","expanded_url":"http:\/\/www.gbiondo.org","display_url":"gbiondo.org","indices":[0,22]}]},"description":{"urls":[]}},"protected":false,"followers_count":133,"friends_count":508,"listed_count":5,"created_at":"Fri Sep 16 12:20:49 +0000 2011","favourites_count":5,"utc_offset":3600,"time_zone":"Amsterdam","geo_enabled":true,"verified":false,"statuses_count":1260,"lang":"en","contributors_enabled":false,"is_translator":false,"is_translation_enabled":false,"profile_background_color":"000000","profile_background_image_url":"http:\/\/abs.twimg.com\/images\/themes\/theme14\/bg.gif","profile_background_image_url_https":"https:\/\/abs.twimg.com\/images\/themes\/theme14\/bg.gif","profile_background_tile":false,"profile_image_url":"http:\/\/pbs.twimg.com\/profile_images\/1545381746\/n646957706_1429695_5560702_normal.jpg","profile_image_url_https":"https:\/\/pbs.twimg.com\/profile_images\/1545381746\/n646957706_1429695_5560702_normal.jpg","profile_link_color":"DD2E44","profile_sidebar_border_color":"000000","profile_sidebar_fill_color":"000000","profile_text_color":"000000","profile_use_background_image":false,"has_extended_profile":true,"default_profile":false,"default_profile_image":false,"following":false,"follow_request_sent":false,"notifications":false},"geo":null,"coordinates":null,"place":null,"contributors":null,"is_quote_status":false,"retweet_count":0,"favorite_count":0,"entities":{"hashtags":[{"text":"Google","indices":[0,7]}],"symbols":[],"user_mentions":[],"urls":[{"url":"http:\/\/t.co\/rwgKPbGu","expanded_url":"http:\/\/bit.ly\/qq1OLI","display_url":"bit.ly\/qq1OLI","indices":[42,62]}]},"favorited":false,"retweeted":false,"possibly_sensitive":false,"possibly_sensitive_appealable":false,"lang":"en"}