{"created_at":"Wed Oct 19 04:02:15 +0000 2011","id":126508433582211072,"id_str":"126508433582211072","text":"I just add my profile on the #Google+ WebGL Globe project. Add yours ! http:\/\/t.co\/lpuc3xot v\u00eda @AddThis","source":"\u003ca href=\"https:\/\/dev.twitter.com\/docs\/tfw\" rel=\"nofollow\"\u003eTwitter for Websites\u003c\/a\u003e","truncated":false,"in_reply_to_status_id":null,"in_reply_to_status_id_str":null,"in_reply_to_user_id":null,"in_reply_to_user_id_str":null,"in_reply_to_screen_name":null,"user":{"id":73701466,"id_str":"73701466","name":"alejandro tapia r","screen_name":"alejandrotr","location":"Cochabamba-Bolivia","description":"Administrador financiero, colombiano","url":null,"entities":{"description":{"urls":[]}},"protected":false,"followers_count":29,"friends_count":105,"listed_count":0,"created_at":"Sat Sep 12 18:21:09 +0000 2009","favourites_count":64,"utc_offset":-14400,"time_zone":"La Paz","geo_enabled":true,"verified":false,"statuses_count":133,"lang":"es","contributors_enabled":false,"is_translator":false,"is_translation_enabled":false,"profile_background_color":"1A1B1F","profile_background_image_url":"http:\/\/abs.twimg.com\/images\/themes\/theme9\/bg.gif","profile_background_image_url_https":"https:\/\/abs.twimg.com\/images\/themes\/theme9\/bg.gif","profile_background_tile":false,"profile_image_url":"http:\/\/pbs.twimg.com\/profile_images\/477424157253459968\/FbODno-3_normal.jpeg","profile_image_url_https":"https:\/\/pbs.twimg.com\/profile_images\/477424157253459968\/FbODno-3_normal.jpeg","profile_banner_url":"https:\/\/pbs.twimg.com\/profile_banners\/73701466\/1371125637","profile_link_color":"2FC2EF","profile_sidebar_border_color":"181A1E","profile_sidebar_fill_color":"252429","profile_text_color":"666666","profile_use_background_image":true,"has_extended_profile":false,"default_profile":false,"default_profile_image":false,"following":false,"follow_request_sent":false,"notifications":false},"geo":null,"coordinates":null,"place":null,"contributors":null,"is_quote_status":false,"retweet_count":0,"favorite_count":0,"entities":{"hashtags":[{"text":"Google","indices":[29,36]}],"symbols":[],"user_mentions":[{"screen_name":"addthis","name":"AddThis","id":15907720,"id_str":"15907720","indices":[96,104]}],"urls":[{"url":"http:\/\/t.co\/lpuc3xot","expanded_url":"http:\/\/www.gplusglobe.com\/#.Tp5LeLvvZZc.twitter","display_url":"gplusglobe.com\/#.Tp5LeLvvZZc.\u2026","indices":[71,91]}]},"favorited":false,"retweeted":false,"possibly_sensitive":false,"possibly_sensitive_appealable":false,"lang":"en"}