{"created_at":"Wed Oct 19 09:34:57 +0000 2011","id":126592158802264064,"id_str":"126592158802264064","text":"#Microsoft discontinued product named #ENSEMBLE STUDIOS on October 14, 2011. Review and comment: http:\/\/t.co\/eJ8a2Msm","source":"\u003ca href=\"http:\/\/www.trademarkia.com\" rel=\"nofollow\"\u003eTrademarkia\u003c\/a\u003e","truncated":false,"in_reply_to_status_id":null,"in_reply_to_status_id_str":null,"in_reply_to_user_id":null,"in_reply_to_user_id_str":null,"in_reply_to_screen_name":null,"user":{"id":74313567,"id_str":"74313567","name":"LF Trademarkia","screen_name":"Trademarkia","location":"Mountain View, California","description":"The Largest Trademark Website In The World. Disclaimer -http:\/\/t.co\/Bz7xXERjbN","url":"http:\/\/t.co\/o1dLHFu9J4","entities":{"url":{"urls":[{"url":"http:\/\/t.co\/o1dLHFu9J4","expanded_url":"http:\/\/www.trademarkia.com","display_url":"trademarkia.com","indices":[0,22]}]},"description":{"urls":[{"url":"http:\/\/t.co\/Bz7xXERjbN","expanded_url":"http:\/\/lawinspiring.com\/disclaimer\/","display_url":"lawinspiring.com\/disclaimer\/","indices":[56,78]}]}},"protected":false,"followers_count":3020,"friends_count":2100,"listed_count":136,"created_at":"Tue Sep 15 00:25:58 +0000 2009","favourites_count":680,"utc_offset":-28800,"time_zone":"Pacific Time (US & Canada)","geo_enabled":true,"verified":false,"statuses_count":5690,"lang":"en","contributors_enabled":false,"is_translator":false,"is_translation_enabled":false,"profile_background_color":"FAF9F7","profile_background_image_url":"http:\/\/pbs.twimg.com\/profile_background_images\/453660001626640385\/KJvHP_MD.jpeg","profile_background_image_url_https":"https:\/\/pbs.twimg.com\/profile_background_images\/453660001626640385\/KJvHP_MD.jpeg","profile_background_tile":false,"profile_image_url":"http:\/\/pbs.twimg.com\/profile_images\/378800000674973713\/e0c354a914326856cb84ca5f3e2d0e65_normal.jpeg","profile_image_url_https":"https:\/\/pbs.twimg.com\/profile_images\/378800000674973713\/e0c354a914326856cb84ca5f3e2d0e65_normal.jpeg","profile_banner_url":"https:\/\/pbs.twimg.com\/profile_banners\/74313567\/1401984987","profile_link_color":"F06400","profile_sidebar_border_color":"FFFFFF","profile_sidebar_fill_color":"DDEEF6","profile_text_color":"333333","profile_use_background_image":true,"has_extended_profile":false,"default_profile":false,"default_profile_image":false,"following":false,"follow_request_sent":false,"notifications":false},"geo":null,"coordinates":null,"place":null,"contributors":null,"is_quote_status":false,"retweet_count":0,"favorite_count":0,"entities":{"hashtags":[{"text":"Microsoft","indices":[0,10]},{"text":"ENSEMBLE","indices":[38,47]}],"symbols":[],"user_mentions":[],"urls":[{"url":"http:\/\/t.co\/eJ8a2Msm","expanded_url":"http:\/\/www.trademarkia.com\/ensemble-studios-78975617.html","display_url":"trademarkia.com\/ensemble-studi\u2026","indices":[97,117]}]},"favorited":false,"retweeted":false,"possibly_sensitive":false,"possibly_sensitive_appealable":false,"lang":"en"}