{"created_at":"Wed Oct 19 11:46:59 +0000 2011","id":126625386565087232,"id_str":"126625386565087232","text":"RT @MuyCanal: MuyCanal: Avanade y Ferranti Computer ofrecen un #ERP basado en #Microsoft Dynamics  http:\/\/t.co\/MaghjzcS @msdynamicsspain #ax","source":"\u003ca href=\"https:\/\/about.twitter.com\/products\/tweetdeck\" rel=\"nofollow\"\u003eTweetDeck\u003c\/a\u003e","truncated":false,"in_reply_to_status_id":null,"in_reply_to_status_id_str":null,"in_reply_to_user_id":null,"in_reply_to_user_id_str":null,"in_reply_to_screen_name":null,"user":{"id":43395434,"id_str":"43395434","name":"Avanade Spain","screen_name":"AvanadeSpain","location":"Madrid; Barcelona; M\u00e1laga","description":"Avanade es proveedor global de soluciones tecnol\u00f3gicas de negocio y servicios gestionados creada por Microsoft y Accenture","url":"http:\/\/t.co\/8iVFWYfaQj","entities":{"url":{"urls":[{"url":"http:\/\/t.co\/8iVFWYfaQj","expanded_url":"http:\/\/www.avanade.com\/es","display_url":"avanade.com\/es","indices":[0,22]}]},"description":{"urls":[]}},"protected":false,"followers_count":1065,"friends_count":683,"listed_count":95,"created_at":"Fri May 29 19:50:45 +0000 2009","favourites_count":32,"utc_offset":3600,"time_zone":"Madrid","geo_enabled":false,"verified":false,"statuses_count":3226,"lang":"es","contributors_enabled":false,"is_translator":false,"is_translation_enabled":false,"profile_background_color":"EEEEEE","profile_background_image_url":"http:\/\/pbs.twimg.com\/profile_background_images\/534697246\/avanade_twitter_background-eeeeee.jpg","profile_background_image_url_https":"https:\/\/pbs.twimg.com\/profile_background_images\/534697246\/avanade_twitter_background-eeeeee.jpg","profile_background_tile":false,"profile_image_url":"http:\/\/pbs.twimg.com\/profile_images\/2162119256\/avanade-twitter-profile_normal.jpg","profile_image_url_https":"https:\/\/pbs.twimg.com\/profile_images\/2162119256\/avanade-twitter-profile_normal.jpg","profile_banner_url":"https:\/\/pbs.twimg.com\/profile_banners\/43395434\/1423668569","profile_link_color":"FF5800","profile_sidebar_border_color":"DBDBDB","profile_sidebar_fill_color":"F5F5F5","profile_text_color":"333333","profile_use_background_image":true,"has_extended_profile":false,"default_profile":false,"default_profile_image":false,"following":false,"follow_request_sent":false,"notifications":false},"geo":null,"coordinates":null,"place":null,"contributors":null,"is_quote_status":false,"retweet_count":2,"favorite_count":0,"entities":{"hashtags":[{"text":"ERP","indices":[63,67]},{"text":"Microsoft","indices":[78,88]},{"text":"ax","indices":[137,140]}],"symbols":[],"user_mentions":[{"screen_name":"MuyCanal","name":"MuyCanal","id":377257161,"id_str":"377257161","indices":[3,12]},{"screen_name":"MSDynamicsSpain","name":"MSDynamicsSpain","id":301335113,"id_str":"301335113","indices":[120,136]}],"urls":[{"url":"http:\/\/t.co\/MaghjzcS","expanded_url":"http:\/\/www.muycanal.com\/?p=17987","display_url":"muycanal.com\/?p=17987","indices":[99,119]}]},"favorited":false,"retweeted":false,"possibly_sensitive":false,"possibly_sensitive_appealable":false,"lang":"es"}