{"created_at":"Wed Oct 19 13:08:52 +0000 2011","id":126645991947513857,"id_str":"126645991947513857","text":"I gave @RyannosaurusRex +K about Microsoft Windows on @klout http:\/\/t.co\/Y33v8wVr #klout #microsoft #windows","source":"\u003ca href=\"https:\/\/dev.twitter.com\/docs\/tfw\" rel=\"nofollow\"\u003eTwitter for Websites\u003c\/a\u003e","truncated":false,"in_reply_to_status_id":null,"in_reply_to_status_id_str":null,"in_reply_to_user_id":null,"in_reply_to_user_id_str":null,"in_reply_to_screen_name":null,"user":{"id":2047701,"id_str":"2047701","name":"Richie Wagner","screen_name":"rdwagner","location":"iPhone: 36.579645,-82.486367","description":"Living life and sharing nuggets of wisdom as I dig them up. Husband, Dad, Rockstar, Disc Golfer, IT RIS\/PACS Adminstrator, Vinyl Record fan, Beer enthusiast...","url":"http:\/\/t.co\/K52QTiWfOg","entities":{"url":{"urls":[{"url":"http:\/\/t.co\/K52QTiWfOg","expanded_url":"http:\/\/www.rdwagner.com","display_url":"rdwagner.com","indices":[0,22]}]},"description":{"urls":[]}},"protected":false,"followers_count":12506,"friends_count":197,"listed_count":148,"created_at":"Fri Mar 23 20:05:56 +0000 2007","favourites_count":91,"utc_offset":-18000,"time_zone":"Eastern Time (US & Canada)","geo_enabled":true,"verified":false,"statuses_count":14662,"lang":"en","contributors_enabled":false,"is_translator":false,"is_translation_enabled":false,"profile_background_color":"2B2816","profile_background_image_url":"http:\/\/pbs.twimg.com\/profile_background_images\/378802284\/x8d647905746d6fc25b8a8c09752467c.jpg","profile_background_image_url_https":"https:\/\/pbs.twimg.com\/profile_background_images\/378802284\/x8d647905746d6fc25b8a8c09752467c.jpg","profile_background_tile":false,"profile_image_url":"http:\/\/pbs.twimg.com\/profile_images\/3080430537\/9f67d562c247d7b0af5f7d15e47f7009_normal.jpeg","profile_image_url_https":"https:\/\/pbs.twimg.com\/profile_images\/3080430537\/9f67d562c247d7b0af5f7d15e47f7009_normal.jpeg","profile_banner_url":"https:\/\/pbs.twimg.com\/profile_banners\/2047701\/1386982457","profile_link_color":"89B5A2","profile_sidebar_border_color":"89B5A2","profile_sidebar_fill_color":"24210E","profile_text_color":"2B2816","profile_use_background_image":true,"has_extended_profile":false,"default_profile":false,"default_profile_image":false,"following":false,"follow_request_sent":false,"notifications":false},"geo":null,"coordinates":null,"place":null,"contributors":null,"is_quote_status":false,"retweet_count":0,"favorite_count":0,"entities":{"hashtags":[{"text":"klout","indices":[82,88]},{"text":"microsoft","indices":[89,99]},{"text":"windows","indices":[100,108]}],"symbols":[],"user_mentions":[{"screen_name":"RyannosaurusRex","name":"Ryan Hayes","id":15887030,"id_str":"15887030","indices":[7,23]},{"screen_name":"klout","name":"Klout","id":15134782,"id_str":"15134782","indices":[54,60]}],"urls":[{"url":"http:\/\/t.co\/Y33v8wVr","expanded_url":"http:\/\/klout.com\/user\/RyannosaurusRex\/topics?n=tw&v=plusk_gave","display_url":"klout.com\/user\/Ryannosau\u2026","indices":[61,81]}]},"favorited":false,"retweeted":false,"possibly_sensitive":false,"possibly_sensitive_appealable":false,"lang":"en"}