{"created_at":"Wed Oct 19 12:01:11 +0000 2011","id":126628957566156800,"id_str":"126628957566156800","text":"Database sizing #Microsoft #SharePoint 2010 #VMware #VMworld http:\/\/t.co\/ZcdTjyrp","source":"\u003ca href=\"http:\/\/twitter.com\/download\/iphone\" rel=\"nofollow\"\u003eTwitter for iPhone\u003c\/a\u003e","truncated":false,"in_reply_to_status_id":null,"in_reply_to_status_id_str":null,"in_reply_to_user_id":null,"in_reply_to_user_id_str":null,"in_reply_to_screen_name":null,"user":{"id":38691981,"id_str":"38691981","name":"Roy Mikes","screen_name":"teovmy","location":"Netherlands","description":"Author of mikes.eu | Dutch | EMC\u00b2 | VMware | VCP3, VCP4-DV, VCP5-DV, VTSP4, VTSP5, VSP5, vExpert, EMC Elect, EMCISA, EMCST, EMCDCA | EMCCA | Tweets are my own","url":"https:\/\/t.co\/uU2MmUZlZC","entities":{"url":{"urls":[{"url":"https:\/\/t.co\/uU2MmUZlZC","expanded_url":"http:\/\/www.mikes.eu","display_url":"mikes.eu","indices":[0,23]}]},"description":{"urls":[]}},"protected":false,"followers_count":2337,"friends_count":385,"listed_count":99,"created_at":"Fri May 08 16:07:26 +0000 2009","favourites_count":55,"utc_offset":3600,"time_zone":"Amsterdam","geo_enabled":true,"verified":false,"statuses_count":25001,"lang":"en","contributors_enabled":false,"is_translator":false,"is_translation_enabled":false,"profile_background_color":"1A1B1F","profile_background_image_url":"http:\/\/abs.twimg.com\/images\/themes\/theme9\/bg.gif","profile_background_image_url_https":"https:\/\/abs.twimg.com\/images\/themes\/theme9\/bg.gif","profile_background_tile":false,"profile_image_url":"http:\/\/pbs.twimg.com\/profile_images\/478217105792577536\/UNH3JFfP_normal.jpeg","profile_image_url_https":"https:\/\/pbs.twimg.com\/profile_images\/478217105792577536\/UNH3JFfP_normal.jpeg","profile_banner_url":"https:\/\/pbs.twimg.com\/profile_banners\/38691981\/1437386245","profile_link_color":"2FC2EF","profile_sidebar_border_color":"181A1E","profile_sidebar_fill_color":"252429","profile_text_color":"666666","profile_use_background_image":true,"has_extended_profile":true,"default_profile":false,"default_profile_image":false,"following":false,"follow_request_sent":false,"notifications":false},"geo":null,"coordinates":null,"place":null,"contributors":null,"is_quote_status":false,"retweet_count":0,"favorite_count":0,"entities":{"hashtags":[{"text":"Microsoft","indices":[16,26]},{"text":"SharePoint","indices":[27,38]},{"text":"VMware","indices":[44,51]},{"text":"VMworld","indices":[52,60]}],"symbols":[],"user_mentions":[],"urls":[],"media":[{"id":126628957570351106,"id_str":"126628957570351106","indices":[61,81],"media_url":"http:\/\/pbs.twimg.com\/media\/AcHgXbJCQAI2_Uw.jpg","media_url_https":"https:\/\/pbs.twimg.com\/media\/AcHgXbJCQAI2_Uw.jpg","url":"http:\/\/t.co\/ZcdTjyrp","display_url":"pic.twitter.com\/ZcdTjyrp","expanded_url":"http:\/\/twitter.com\/teovmy\/status\/126628957566156800\/photo\/1","type":"photo","sizes":{"medium":{"w":600,"h":448,"resize":"fit"},"small":{"w":340,"h":254,"resize":"fit"},"thumb":{"w":150,"h":150,"resize":"crop"},"large":{"w":1024,"h":765,"resize":"fit"}}}]},"extended_entities":{"media":[{"id":126628957570351106,"id_str":"126628957570351106","indices":[61,81],"media_url":"http:\/\/pbs.twimg.com\/media\/AcHgXbJCQAI2_Uw.jpg","media_url_https":"https:\/\/pbs.twimg.com\/media\/AcHgXbJCQAI2_Uw.jpg","url":"http:\/\/t.co\/ZcdTjyrp","display_url":"pic.twitter.com\/ZcdTjyrp","expanded_url":"http:\/\/twitter.com\/teovmy\/status\/126628957566156800\/photo\/1","type":"photo","sizes":{"medium":{"w":600,"h":448,"resize":"fit"},"small":{"w":340,"h":254,"resize":"fit"},"thumb":{"w":150,"h":150,"resize":"crop"},"large":{"w":1024,"h":765,"resize":"fit"}}}]},"favorited":false,"retweeted":false,"possibly_sensitive":false,"possibly_sensitive_appealable":false,"lang":"en"}