{"created_at":"Wed Oct 19 19:37:41 +0000 2011","id":126743843348561920,"id_str":"126743843348561920","text":"#Microsoft to Slash its #Water Impact in Quincy, Washington - http:\/\/t.co\/0R5LMHZj","source":"\u003ca href=\"http:\/\/bitly.com\" rel=\"nofollow\"\u003ebitly bitlink\u003c\/a\u003e","truncated":false,"in_reply_to_status_id":null,"in_reply_to_status_id_str":null,"in_reply_to_user_id":null,"in_reply_to_user_id_str":null,"in_reply_to_screen_name":null,"user":{"id":84607672,"id_str":"84607672","name":"Patrick Vowell","screen_name":"pvowell","location":"San Luis Obispo, CA","description":"Patrick is dedicated to matters concerning environmental compliance, water quality, and the water-energy nexus.","url":null,"entities":{"description":{"urls":[]}},"protected":false,"followers_count":699,"friends_count":548,"listed_count":37,"created_at":"Fri Oct 23 14:45:22 +0000 2009","favourites_count":66,"utc_offset":-28800,"time_zone":"Pacific Time (US & Canada)","geo_enabled":false,"verified":false,"statuses_count":9820,"lang":"en","contributors_enabled":false,"is_translator":false,"is_translation_enabled":false,"profile_background_color":"E4E9EB","profile_background_image_url":"http:\/\/pbs.twimg.com\/profile_background_images\/344918034409863534\/78a719b0030efd0e75d8db962f4fa4f1.jpeg","profile_background_image_url_https":"https:\/\/pbs.twimg.com\/profile_background_images\/344918034409863534\/78a719b0030efd0e75d8db962f4fa4f1.jpeg","profile_background_tile":false,"profile_image_url":"http:\/\/pbs.twimg.com\/profile_images\/1587539286\/FotoFlexer_Photo_normal.jpg","profile_image_url_https":"https:\/\/pbs.twimg.com\/profile_images\/1587539286\/FotoFlexer_Photo_normal.jpg","profile_banner_url":"https:\/\/pbs.twimg.com\/profile_banners\/84607672\/1413815594","profile_link_color":"0084B4","profile_sidebar_border_color":"FFFFFF","profile_sidebar_fill_color":"DDEEF6","profile_text_color":"333333","profile_use_background_image":true,"has_extended_profile":false,"default_profile":false,"default_profile_image":false,"following":false,"follow_request_sent":false,"notifications":false},"geo":null,"coordinates":null,"place":null,"contributors":null,"is_quote_status":false,"retweet_count":0,"favorite_count":0,"entities":{"hashtags":[{"text":"Microsoft","indices":[0,10]},{"text":"Water","indices":[24,30]}],"symbols":[],"user_mentions":[],"urls":[{"url":"http:\/\/t.co\/0R5LMHZj","expanded_url":"http:\/\/bit.ly\/o6IRL5","display_url":"bit.ly\/o6IRL5","indices":[62,82]}]},"favorited":false,"retweeted":false,"possibly_sensitive":false,"possibly_sensitive_appealable":false,"lang":"en"}