{"created_at":"Thu Oct 20 04:32:07 +0000 2011","id":126878337342771201,"id_str":"126878337342771201","text":"Buenas Noches a Todos!!! Llego mi momento. Momento #Twitter de reflexiones y analisis. Pensamientos encontrados en lo profundo de la noche.","source":"\u003ca href=\"http:\/\/blackberry.com\/twitter\" rel=\"nofollow\"\u003eTwitter for BlackBerry\u00ae\u003c\/a\u003e","truncated":false,"in_reply_to_status_id":null,"in_reply_to_status_id_str":null,"in_reply_to_user_id":null,"in_reply_to_user_id_str":null,"in_reply_to_screen_name":null,"user":{"id":278214273,"id_str":"278214273","name":"Fernando Martins","screen_name":"fermartinsba","location":"Buenos Aires City","description":"Una de las mejores cosas en la vida es darte cuenta de que eres feliz, sin tener las cosas que cre\u00edas que m\u00e1s necesitabas para vivir.","url":"http:\/\/t.co\/OYeY93j0Fm","entities":{"url":{"urls":[{"url":"http:\/\/t.co\/OYeY93j0Fm","expanded_url":"http:\/\/www.mascarnaval.com","display_url":"mascarnaval.com","indices":[0,22]}]},"description":{"urls":[]}},"protected":false,"followers_count":405,"friends_count":1481,"listed_count":2,"created_at":"Wed Apr 06 20:56:28 +0000 2011","favourites_count":326,"utc_offset":-10800,"time_zone":"Buenos Aires","geo_enabled":true,"verified":false,"statuses_count":7105,"lang":"es","contributors_enabled":false,"is_translator":false,"is_translation_enabled":false,"profile_background_color":"C0DEED","profile_background_image_url":"http:\/\/pbs.twimg.com\/profile_background_images\/229125241\/26987_372932941341_726011341_3736307_1925283_n.jpg","profile_background_image_url_https":"https:\/\/pbs.twimg.com\/profile_background_images\/229125241\/26987_372932941341_726011341_3736307_1925283_n.jpg","profile_background_tile":false,"profile_image_url":"http:\/\/pbs.twimg.com\/profile_images\/541785709519319041\/WqlSyf5B_normal.jpeg","profile_image_url_https":"https:\/\/pbs.twimg.com\/profile_images\/541785709519319041\/WqlSyf5B_normal.jpeg","profile_banner_url":"https:\/\/pbs.twimg.com\/profile_banners\/278214273\/1445288888","profile_link_color":"0084B4","profile_sidebar_border_color":"C0DEED","profile_sidebar_fill_color":"DDEEF6","profile_text_color":"333333","profile_use_background_image":true,"has_extended_profile":false,"default_profile":false,"default_profile_image":false,"following":false,"follow_request_sent":false,"notifications":false},"geo":null,"coordinates":null,"place":null,"contributors":null,"is_quote_status":false,"retweet_count":0,"favorite_count":0,"entities":{"hashtags":[{"text":"Twitter","indices":[51,59]}],"symbols":[],"user_mentions":[],"urls":[]},"favorited":false,"retweeted":false,"lang":"es"}