{"created_at":"Thu Oct 20 04:12:32 +0000 2011","id":126873407487881217,"id_str":"126873407487881217","text":"vo sair daki do #twitter j\u00e1 :) s\u00f3 vo ver uns videos aki , e j\u00e1 to indo ,","source":"\u003ca href=\"http:\/\/twitter.com\" rel=\"nofollow\"\u003eTwitter Web Client\u003c\/a\u003e","truncated":false,"in_reply_to_status_id":null,"in_reply_to_status_id_str":null,"in_reply_to_user_id":null,"in_reply_to_user_id_str":null,"in_reply_to_screen_name":null,"user":{"id":299464151,"id_str":"299464151","name":"Nathalie Mendes","screen_name":"Nathali_Mendes","location":"Curitiba, Paran\u00e1","description":"Ga\u00facha \u2661 19!","url":null,"entities":{"description":{"urls":[]}},"protected":false,"followers_count":384,"friends_count":285,"listed_count":1,"created_at":"Mon May 16 04:02:04 +0000 2011","favourites_count":55,"utc_offset":-10800,"time_zone":"Santiago","geo_enabled":true,"verified":false,"statuses_count":25687,"lang":"pt","contributors_enabled":false,"is_translator":false,"is_translation_enabled":false,"profile_background_color":"DBE9ED","profile_background_image_url":"http:\/\/abs.twimg.com\/images\/themes\/theme17\/bg.gif","profile_background_image_url_https":"https:\/\/abs.twimg.com\/images\/themes\/theme17\/bg.gif","profile_background_tile":false,"profile_image_url":"http:\/\/pbs.twimg.com\/profile_images\/654123751907401729\/7k5g8G_p_normal.jpg","profile_image_url_https":"https:\/\/pbs.twimg.com\/profile_images\/654123751907401729\/7k5g8G_p_normal.jpg","profile_banner_url":"https:\/\/pbs.twimg.com\/profile_banners\/299464151\/1445017506","profile_link_color":"CC3366","profile_sidebar_border_color":"DBE9ED","profile_sidebar_fill_color":"E6F6F9","profile_text_color":"333333","profile_use_background_image":true,"has_extended_profile":true,"default_profile":false,"default_profile_image":false,"following":false,"follow_request_sent":false,"notifications":false},"geo":null,"coordinates":null,"place":null,"contributors":null,"is_quote_status":false,"retweet_count":0,"favorite_count":0,"entities":{"hashtags":[{"text":"twitter","indices":[16,24]}],"symbols":[],"user_mentions":[],"urls":[]},"favorited":false,"retweeted":false,"lang":"pt"}